npc_ephys/LFP.py
npc_ephys/__init__.py
npc_ephys/barcodes.py
npc_ephys/newscale.py
npc_ephys/openephys.py
npc_ephys/py.typed
npc_ephys/settings_xml.py
npc_ephys/spikeinterface.py
npc_ephys/units.py
npc_ephys-0.1.37.dist-info/licenses/LICENSE
npc_ephys-0.1.37.dist-info/METADATA
npc_ephys-0.1.37.dist-info/WHEEL
npc_ephys-0.1.37.dist-info/top_level.txt
npc_ephys-0.1.37.dist-info/RECORD
