Metadata-Version: 2.4
Name: npc-ephys
Version: 0.1.37
Summary: Tools for accessing and processing raw ephys data, compatible with data in the cloud.
Author-email: Ben Hardcastle <ben.hardcastle@alleninstitue.org>
License: MIT
Project-URL: Repository, https://github.com/AllenInstitute/npc_ephys
Project-URL: Issues, https://github.com/AllenInstitute/npc_ephys/issues
Classifier: Development Status :: 3 - Alpha
Classifier: Programming Language :: Python :: 3
Classifier: Programming Language :: Python :: 3.9
Classifier: Programming Language :: Python :: 3.10
Classifier: Programming Language :: Python :: 3.11
Classifier: License :: OSI Approved :: MIT License
Classifier: Operating System :: Microsoft :: Windows
Classifier: Operating System :: POSIX :: Linux
Requires-Python: >=3.9
License-File: LICENSE
Requires-Dist: npc-sync>=0.1.12
Requires-Dist: zarr<2.18.1
Requires-Dist: pandas>=2.2.0
Requires-Dist: tqdm>=4.66.1
Requires-Dist: npc-lims>=0.1.73
Requires-Dist: wavpack-numcodecs!=0.2.0,>=0.1.5
Requires-Dist: npc-io>=0.1.26
Requires-Dist: pynwb>=2.8.0
Requires-Dist: hdmf-zarr-bjh==0.8.1.post1
Requires-Dist: polars>=0.20.26
Requires-Dist: pyarrow>=14.0
Dynamic: license-file
